[
	{
		"__TYPE__": "SharedSliceContent",
		"variation": "default",
		"primary": {
			"heading": {
				"__TYPE__": "StructuredTextContent",
				"value": [
					{
						"type": "heading2",
						"content": {
							"text": "Report"
						}
					}
				]
			},
			"body": {
				"__TYPE__": "StructuredTextContent",
				"value": [
					{
						"type": "paragraph",
						"content": {
							"text": "Ipsum amet nostrud aute. Laboris enim aliquip reprehenderit adipisicing proident. Do ullamco aliqua amet ea quis elit cupidatat sint velit eiusmod."
						}
					}
				]
			},
			"bento": {
				"__TYPE__": "GroupContentType",
				"value": [
					{
						"__TYPE__": "GroupItemContent",
						"value": [
							[
								"title",
								{
									"__TYPE__": "StructuredTextContent",
									"value": [
										{
											"type": "heading3",
											"content": {
												"text": "Whether"
											}
										}
									]
								}
							],
							[
								"body",
								{
									"__TYPE__": "StructuredTextContent",
									"value": [
										{
											"type": "paragraph",
											"content": {
												"text": "Ullamco minim proident reprehenderit voluptate enim duis consequat dolore cupidatat eiusmod. Ea minim fugiat dolor eiusmod Lorem ea nulla eu."
											}
										}
									]
								}
							],
							[
								"image",
								{
									"origin": {
										"id": "main",
										"url": "https://images.unsplash.com/photo-1576662712957-9c79ae1280f8",
										"width": 3456,
										"height": 3456
									},
									"url": "https://images.unsplash.com/photo-1576662712957-9c79ae1280f8",
									"width": 3456,
									"height": 3456,
									"edit": {
										"zoom": 1,
										"crop": {
											"x": 0,
											"y": 0
										},
										"background": "transparent"
									},
									"credits": null,
									"alt": null,
									"__TYPE__": "ImageContent",
									"thumbnails": {}
								}
							],
							[
								"wide",
								{
									"__TYPE__": "BooleanContent",
									"value": false
								}
							]
						]
					}
				]
			}
		},
		"items": []
	}
]